ippc_model/__init__.py
ippc_model/ippc_activity.py
ippc_model/ippc_common.py
ippc_model/ippc_container.py
ippc_model/ippc_document.py
ippc_model/ippc_equipment.py
ippc_model/ippc_expert.py
ippc_model-1.0.2.dist-info/licenses/LICENSE
ippc_model-1.0.2.dist-info/METADATA
ippc_model-1.0.2.dist-info/WHEEL
ippc_model-1.0.2.dist-info/top_level.txt
ippc_model-1.0.2.dist-info/RECORD
