Metadata-Version: 2.4
Name: ippc-model
Version: 1.0.2
Summary: IPPC Data Model
Author-email: Data Developer <info@sysnet.cz>
Project-URL: Homepage, https://github.com/SYSNET-CZ/models/tree/main/ippc
Classifier: Development Status :: 4 - Beta
Classifier: Programming Language :: Python :: 3
Classifier: Intended Audience :: Developers
Classifier: License :: Free For Home Use
Classifier: Natural Language :: Czech
Classifier: Operating System :: OS Independent
Classifier: Topic :: Software Development :: Libraries
Requires-Python: >=3.10
License-File: LICENSE
Requires-Dist: sysnet-pyutils>=1.3.10
Requires-Dist: pydantic~=2.11.7
Dynamic: license-file
